{
    "versions": [
        {
            "package_version": "1.0.0",
            "download_url": "https://github.com/Mekurushi/pokepark_ap_poptracker/releases/download/1.0.0/pokepark_ap_poptracker.zip",
            "sha256": "61d1d98d0c66dc20e638c516bd1cb66bad4801ed70bef6c60555c284c49edcae",
            "changelog": [
                "initial release"
            ]
        },
        {
            "package_version": "1.1.0",
            "download_url": "https://github.com/Mekurushi/pokepark_ap_poptracker/releases/download/1.1.0/v1.1.0.zip",
            "sha256": "92dc9b474208da049fc3f7079838f1ed3bd03d95ea08cf235a76b308e9bbcb90",
            "changelog": [
                "updated logic to match 1.x.x",
                "added randomized entrances support",
                "New Attraction Assets"
            ]
        },
        {
            "package_version": "1.1.1",
            "download_url": "https://github.com/Mekurushi/pokepark_ap_poptracker/releases/download/1.1.1/v1.1.1.zip",
            "sha256": "9dd8b43fdfb64d8b67a10493fb90dd0e6c6da2c877755eaa01a078c0f909dfba",
            "changelog": [
                "fixed flygon rule"
            ]
        },
        {
            "package_version": "1.2.0",
            "download_url": "https://github.com/Mekurushi/pokepark_ap_poptracker/releases/download/1.2.0/pokepark_ap_poptracker.zip",
            "sha256": "68517c9106c4fbffce623a7acf26bfa9f356f98c215362fc7aa352b6a607e484",
            "changelog": [
                "fixed loading goal setting from slot data",
                "added tangrowth location on map",
                "synced logic with apworld",
                "fixed parent usage in entrances",
                "improved layout scaling",
                "added basic location icons"
            ]
        },
        {
            "package_version": "1.2.1",
            "download_url": "https://github.com/Mekurushi/pokepark_ap_poptracker/releases/download/1.2.1/pokepark_ap_poptracker.zip",
            "sha256": "3058566bb451b9142d281f8bf759ef044ec6b1529c9a48b7d31a7c1512e5031c",
            "changelog": [
                "Display entrances",
                "UT locations support",
                "renamed maps user-friendly",
                "logic considers that double dash unlocks dash",
                "added overview tab",
                "increased glaceon requirement"
            ]
        },
        {
            "package_version": "1.2.2",
            "download_url": "https://github.com/Mekurushi/pokepark_ap_poptracker/releases/download/1.2.2/pokepark_ap_poptracker.zip",
            "sha256": "d54219ca448a785c04b75317b56e9d8e13b317bfe8f6350f842c752e1f9a0ea9",
            "changelog": [
                "fixed flareon location rule"
            ]
        },
        {
            "package_version": "1.2.3",
            "download_url": "https://github.com/Mekurushi/pokepark_ap_poptracker/releases/download/1.2.3/pokepark_ap_poptracker.zip",
            "sha256": "3b7d49e8311c390ace710def69e5507898ac3e8d6ee768a5eb46d25e91108f76",
            "changelog": [
                "fixed rhyperior bumper burn auto swap + pokepark entrance auto swap"
            ]
        }
    ]
}